{
  "protocol_version" : "0.0.2",
  "configuration" : {
    "version" : "5.18.0.240 (tarball)",
    "tlc" : "__thread",
    "sigsgev" : "altstack",
    "notifications" : "epoll",
    "architecture" : "amd64",
    "disabled_features" : "none",
    "smallconfig" : "disabled",
    "bigarrays" : "disabled",
    "softdebug" : "enabled",
    "interpreter" : "enabled",
    "llvm_support" : "disabled",
    "suspend" : "preemptive"
  },
  "memory" : {
    "minor_gc_time" : "0",
    "major_gc_time" : "0",
    "minor_gc_count" : "0",
    "major_gc_count" : "0",
    "major_gc_time_concurrent" : "0"
 },
  "threads" : [
 {
    "is_managed" : false,
    "crashed" : true,
    "managed_thread_ptr" : "0x0",
    "native_thread_id" : "0x7f9fc1307900",
    "thread_info_addr" : "0x0",
    "thread_name" : "Godot_v3.1-stab",
    "ctx" : {
      "IP" : "0x7f9fc04bb238",
      "SP" : "0x7ffeee38be18",
      "BP" : "(nil)"
  },
    "unmanaged_frames" : [
  {
      "native_address" : "unregistered"
   }

  ]
 },
 {
    "is_managed" : false,
    "crashed" : false,
    "managed_thread_ptr" : "0x0",
    "native_thread_id" : "0x7f9fa5ac7700",
    "thread_info_addr" : "0x0",
    "thread_name" : "Finalizer",
    "ctx" : {
      "IP" : "0x7f9fc0f74827",
      "SP" : "0x7f9fa5ac6b30",
      "BP" : "0x451f7c0"
  },
    "unmanaged_frames" : [
  {
      "native_address" : "unregistered"
   }

  ]
 }
 ]
}